OpenPinch/__init__.py
OpenPinch/main.py
OpenPinch/analysis/__init__.py
OpenPinch/analysis/capital_cost_and_area_targeting.py
OpenPinch/analysis/data_preparation.py
OpenPinch/analysis/direct_integration_entry.py
OpenPinch/analysis/energy_transfer_analysis.py
OpenPinch/analysis/exergy_targeting.py
OpenPinch/analysis/gcc_manipulation.py
OpenPinch/analysis/graph_data.py
OpenPinch/analysis/heat_pump_targeting.py
OpenPinch/analysis/indirect_integration_entry.py
OpenPinch/analysis/power_cogeneration_analysis.py
OpenPinch/analysis/problem_table_analysis.py
OpenPinch/analysis/temperature_driving_force.py
OpenPinch/analysis/utility_targeting.py
OpenPinch/classes/__init__.py
OpenPinch/classes/brayton_heat_pump.py
OpenPinch/classes/energy_target.py
OpenPinch/classes/pinch_problem.py
OpenPinch/classes/problem_table.py
OpenPinch/classes/simple_heat_pump.py
OpenPinch/classes/stream.py
OpenPinch/classes/stream_collection.py
OpenPinch/classes/value.py
OpenPinch/classes/zone.py
OpenPinch/examples/recreate_json.py
OpenPinch/examples/OpenPinchWkbs/illustrative.xlsb
OpenPinch/examples/OpenPinchWkbs/illustrative_retrofit.xlsb
OpenPinch/examples/OpenPinchWkbs/locally_integrated.xlsb
OpenPinch/examples/OpenPinchWkbs/only_cold.xlsb
OpenPinch/examples/OpenPinchWkbs/only_hot.xlsb
OpenPinch/examples/OpenPinchWkbs/paper_plant.xlsb
OpenPinch/examples/OpenPinchWkbs/paper_plant_retrofit.xlsb
OpenPinch/examples/OpenPinchWkbs/potatoe-simple.xlsb
OpenPinch/examples/OpenPinchWkbs/pulp_mill.xlsb
OpenPinch/examples/OpenPinchWkbs/refinery.xlsb
OpenPinch/examples/OpenPinchWkbs/refinery_retrofit.xlsb
OpenPinch/examples/OpenPinchWkbs/UnderReview/Chocolote Factory.xlsb
OpenPinch/examples/OpenPinchWkbs/UnderReview/Dairy Factory.xlsb
OpenPinch/examples/OpenPinchWkbs/UnderReview/Meat Processing Factory.xlsb
OpenPinch/examples/OpenPinchWkbs/UnderReview/~$Dairy Factory.xlsb
OpenPinch/examples/OpenPinchWkbs/custom_json/new_example_1.xlsb
OpenPinch/examples/OpenPinchWkbs/custom_json/new_example_2.xlsb
openpinch-0.0.26.dist-info/METADATA
openpinch-0.0.26.dist-info/WHEEL
openpinch-0.0.26.dist-info/licenses/LICENSE
openpinch-0.0.26.dist-info/RECORD
