Metadata-Version: 2.4
Name: OpenPinch
Version: 0.0.26
Summary: An advanced pinch analysis and total site integration toolkit
Project-URL: Homepage, https://github.com/waikato-ahuora-smart-energy-systems/OpenPinch
Project-URL: Issues, https://github.com/waikato-ahuora-smart-energy-systems/OpenPinch/issues
Author-email: Tim Walmsley <tim.walmsley@waikato.ac.nz>
License-Expression: MIT
License-File: LICENSE
Classifier: Operating System :: OS Independent
Classifier: Programming Language :: Python :: 3.11
Classifier: Programming Language :: Python :: 3.12
Requires-Python: >=3.11
Requires-Dist: coolprop
Requires-Dist: matplotlib
Requires-Dist: numpy
Requires-Dist: openpyxl
Requires-Dist: pandas
Requires-Dist: pint
Requires-Dist: plotly
Requires-Dist: pydantic
Requires-Dist: pyxlsb
Requires-Dist: scipy
Requires-Dist: streamlit
Requires-Dist: tespy
Provides-Extra: dev
Requires-Dist: black>=23.9; extra == 'dev'
Requires-Dist: ruff>=0.1.8; extra == 'dev'
